pylookyloo/__init__.py
pylookyloo/api.py
pylookyloo/py.typed
pylookyloo-1.36.2.dist-info/METADATA
pylookyloo-1.36.2.dist-info/WHEEL
pylookyloo-1.36.2.dist-info/entry_points.txt
pylookyloo-1.36.2.dist-info/licenses/LICENSE
pylookyloo-1.36.2.dist-info/RECORD
