Metadata-Version: 2.4
Name: pylookyloo
Version: 1.36.2
Summary: Python CLI and module for Lookyloo
License-Expression: GPL-2.0-or-later
License-File: LICENSE
Author: Raphaël Vinot
Author-email: raphael.vinot@circl.lu
Requires-Python: >=3.10
Classifier: Development Status :: 5 - Production/Stable
Classifier: Environment :: Console
Classifier: Intended Audience :: Information Technology
Classifier: Intended Audience :: Science/Research
Classifier: Intended Audience :: Telecommunications Industry
Classifier: Operating System :: POSIX :: Linux
Classifier: Programming Language :: Python :: 3
Classifier: Programming Language :: Python :: 3.10
Classifier: Programming Language :: Python :: 3.11
Classifier: Programming Language :: Python :: 3.12
Classifier: Programming Language :: Python :: 3.13
Classifier: Programming Language :: Python :: 3.14
Classifier: Topic :: Internet
Classifier: Topic :: Security
Provides-Extra: docs
Provides-Extra: examples
Requires-Dist: Sphinx (>=9.1.0) ; (python_version >= "3.12") and (extra == "docs")
Requires-Dist: pylacus (>=1.21.0) ; extra == "examples"
Requires-Dist: requests (>=2.32.5)
Project-URL: Documentation, https://pylookyloo.readthedocs.io/en/latest/
Project-URL: Repository, https://github.com/lookyloo/PyLookyloo
Project-URL: issues, https://github.com/lookyloo/PyLookyloo/issues
